printPro/__init__.py
printPro/printPro.py
print_pro_debug-0.1.0.dist-info/licenses/LICENSE
print_pro_debug-0.1.0.dist-info/METADATA
print_pro_debug-0.1.0.dist-info/WHEEL
print_pro_debug-0.1.0.dist-info/top_level.txt
print_pro_debug-0.1.0.dist-info/RECORD
