Metadata-Version: 2.4
Name: print-pro-debug
Version: 0.1.0
Summary: 用于调试输出的高级日志工具
Home-page: https://github.com/afk101/printPro
Author: GDluCk
Author-email: 1477482440@qq.com
Classifier: Programming Language :: Python :: 3
Classifier: License :: OSI Approved :: MIT License
Classifier: Operating System :: OS Independent
Requires-Python: >=3.6
License-File: LICENSE
Requires-Dist: psutil
Dynamic: author
Dynamic: author-email
Dynamic: classifier
Dynamic: description
Dynamic: description-content-type
Dynamic: home-page
Dynamic: license-file
Dynamic: requires-dist
Dynamic: requires-python
Dynamic: summary
